multi_data_loader/.DS_Store
multi_data_loader/__init__.py
multi_data_loader/bases.py
multi_data_loader/data_loader.py
multi_data_loader-0.0.3.dist-info/METADATA
multi_data_loader-0.0.3.dist-info/WHEEL
multi_data_loader-0.0.3.dist-info/licenses/LICENSE
multi_data_loader-0.0.3.dist-info/RECORD
